{
    "María": [
        "08:00",
        "16:00"
    ],
    "Juan": [
        "09:00",
        "17:00"
    ],
    "Lucía": [
        "07:30",
        "15:30"
    ],
    "Diego": [
        "10:00",
        "18:00"
    ],
    "Ana": [
        "08:00",
        "14:00"
    ],
    "Raúl": [
        "12:00",
        "20:00"
    ],
    "Sofía": [
        "14:00",
        "22:00"
    ],
    "Carlos": [
        "06:00",
        "14:00"
    ],
    "Laura": [
        "09:30",
        "17:30"
    ],
    "Pablo": [
        "16:00",
        "00:00"
    ],
    "Elena": [
        "11:00",
        "19:00"
    ],
    "Andrés": [
        "13:00",
        "21:00"
    ],
    "Clara": [
        "07:00",
        "15:00"
    ],
    "Hugo": [
        "15:00",
        "23:00"
    ],
    "Valeria": [
        "08:30",
        "16:30"
    ],
    "Martín": [
        "09:00",
        "17:00"
    ],
    "Irene": [
        "10:30",
        "18:30"
    ],
    "Javier": [
        "06:30",
        "14:30"
    ],
    "Carmen": [
        "13:00",
        "21:00"
    ],
    "Pedro": [
        "11:30",
        "19:30"
    ],
    "Adriana": [
        "07:45",
        "15:45"
    ],
    "Tomás": [
        "08:00",
        "16:00"
    ],
    "Natalia": [
        "12:30",
        "20:30"
    ],
    "Sergio": [
        "14:30",
        "22:30"
    ],
    "Marta": [
        "10:00",
        "18:00"
    ],
    "Víctor": [
        "09:15",
        "17:15"
    ],
    "Isabel": [
        "07:00",
        "15:00"
    ],
    "Rosa": [
        "16:00",
        "00:00"
    ],
    "Samuel": [
        "05:30",
        "13:30"
    ],
    "Julia": [
        "11:00",
        "19:00"
    ],
    "Rubén": [
        "13:30",
        "21:30"
    ],
    "Noelia": [
        "08:15",
        "16:15"
    ],
    "Manuel": [
        "09:45",
        "17:45"
    ],
    "Patricia": [
        "10:00",
        "18:00"
    ],
    "Cristina": [
        "06:00",
        "14:00"
    ],
    "Fernando": [
        "14:00",
        "22:00"
    ],
    "Esteban": [
        "07:30",
        "15:30"
    ],
    "Alba": [
        "12:00",
        "20:00"
    ],
    "David": [
        "11:15",
        "19:15"
    ],
    "Gloria": [
        "08:45",
        "16:45"
    ]
}